pywdgen/__init__.py
pywdgen/checker.py
pywdgen/eval.py
pywdgen/generator.py
pywdgen/hasher.py
pywdgen/main.py
pywdgen-0.0.6.dist-info/LICENSE
pywdgen-0.0.6.dist-info/METADATA
pywdgen-0.0.6.dist-info/WHEEL
pywdgen-0.0.6.dist-info/entry_points.txt
pywdgen-0.0.6.dist-info/top_level.txt
pywdgen-0.0.6.dist-info/RECORD
